torrentcm/__init__.py
torrentcm/torrentcm.py
torrentcm-0.0.8.dist-info/LICENCE
torrentcm-0.0.8.dist-info/METADATA
torrentcm-0.0.8.dist-info/WHEEL
torrentcm-0.0.8.dist-info/entry_points.txt
torrentcm-0.0.8.dist-info/top_level.txt
torrentcm-0.0.8.dist-info/RECORD
